kb_bot/__init__.py
kb_bot/bot.py
kb_bot/chunkers/__init__.py
kb_bot/chunkers/agentic.py
kb_bot/chunkers/basic.py
kb_bot/chunkers/chunker.py
kb_bot/chunkers/semantic.py
kb_bot/db/__init__.py
kb_bot/db/tidb.py
kb_bot/embedding/__init__.py
kb_bot/embedding/oai.py
kb_bot/llm/__init__.py
kb_bot/llm/oai.py
kb_bot/scraper/__init__.py
kb_bot/scraper/file.py
kb_bot/scraper/web.py
kb_bot.core-0.1.21.dist-info/LICENSE
kb_bot.core-0.1.21.dist-info/METADATA
kb_bot.core-0.1.21.dist-info/WHEEL
kb_bot.core-0.1.21.dist-info/top_level.txt
kb_bot.core-0.1.21.dist-info/RECORD
