Metadata-Version: 2.1
Name: kb-bot.core
Version: 0.1.21
Summary: Library to build a bot from Knowledge Base
Author-email: Arjun G <arjun@arjun-g.com>
Project-URL: Homepage, https://github.com/arjun-g/kb-bot.core
Project-URL: Issues, https://github.com/arjun-g/kb-bot.core/issues
Classifier: Programming Language :: Python :: 3
Classifier: License :: OSI Approved :: MIT License
Classifier: Operating System :: OS Independent
Requires-Python: >=3.11
License-File: LICENSE
Requires-Dist: beautifulsoup4 ==4.12.3
Requires-Dist: crochet ==2.1.1
Requires-Dist: llama-index ==0.10.68
Requires-Dist: numpy ==1.26.4
Requires-Dist: openai ==1.42.0
Requires-Dist: peewee ==3.16.3
Requires-Dist: pillow ==10.4.0
Requires-Dist: pydantic ==2.8.2
Requires-Dist: PyMySQL ==1.1.0
Requires-Dist: pypdf ==4.3.1
Requires-Dist: python-dotenv ==1.0.0
Requires-Dist: tidb-vector ==0.0.11
Requires-Dist: Scrapy ==2.11.2
